scribeutil/__init__.py
scribeutil/datatool.py
scribeutil/errors.py
scribeutil/logtracker.py
scribeutil-0.0.3.dist-info/LICENSE
scribeutil-0.0.3.dist-info/METADATA
scribeutil-0.0.3.dist-info/WHEEL
scribeutil-0.0.3.dist-info/top_level.txt
scribeutil-0.0.3.dist-info/RECORD
